connectlib/__init__.py
connectlib/__version__.py
connectlib/dependency.py
connectlib/evaluation_strategy.py
connectlib/exceptions.py
connectlib/experiment.py
connectlib/logger.py
connectlib/model_loading.py
connectlib/schemas.py
connectlib/algorithms/__init__.py
connectlib/algorithms/algo.py
connectlib/algorithms/pytorch/__init__.py
connectlib/algorithms/pytorch/torch_base_algo.py
connectlib/algorithms/pytorch/torch_fed_avg_algo.py
connectlib/algorithms/pytorch/torch_newton_raphson_algo.py
connectlib/algorithms/pytorch/torch_scaffold_algo.py
connectlib/algorithms/pytorch/torch_single_organization_algo.py
connectlib/algorithms/pytorch/weight_manager.py
connectlib/index_generator/__init__.py
connectlib/index_generator/base.py
connectlib/index_generator/np_index_generator.py
connectlib/nodes/__init__.py
connectlib/nodes/aggregation_node.py
connectlib/nodes/node.py
connectlib/nodes/test_data_node.py
connectlib/nodes/train_data_node.py
connectlib/nodes/references/__init__.py
connectlib/nodes/references/local_state.py
connectlib/nodes/references/shared_state.py
connectlib/remote/__init__.py
connectlib/remote/connect_tools_methods.py
connectlib/remote/decorators.py
connectlib/remote/operations.py
connectlib/remote/remote_struct.py
connectlib/remote/register/__init__.py
connectlib/remote/register/generate_wheel.py
connectlib/remote/register/register.py
connectlib/remote/serializers/__init__.py
connectlib/remote/serializers/pickle_serializer.py
connectlib/remote/serializers/serializer.py
connectlib/strategies/__init__.py
connectlib/strategies/fed_avg.py
connectlib/strategies/newton_raphson.py
connectlib/strategies/scaffold.py
connectlib/strategies/single_organization.py
connectlib/strategies/strategy.py
connectlib-0.21.7.dist-info/METADATA
connectlib-0.21.7.dist-info/WHEEL
connectlib-0.21.7.dist-info/top_level.txt
connectlib-0.21.7.dist-info/RECORD
