Metadata-Version: 2.1
Name: connectlib
Version: 0.21.7
Summary: Federated Learning library
Home-page: https://owkin-connectlib.readthedocs-hosted.com/en/latest/
Author: Owkin
Author-email: flow@owkin.com
License: Apache 2.0
Keywords: connectlib
Platform: UNKNOWN
Classifier: Intended Audience :: Developers
Classifier: Topic :: Utilities
Classifier: Natural Language :: English
Classifier: Operating System :: OS Independent
Classifier: Programming Language :: Python :: 3.7
Classifier: Programming Language :: Python :: 3.8
Classifier: Programming Language :: Python :: 3.9
Classifier: Programming Language :: Python :: 3.10
Requires-Python: >=3.7
Requires-Dist: numpy (>=1.20.3)
Requires-Dist: cloudpickle (>=1.6.0)
Requires-Dist: substra (~=0.29.0)
Requires-Dist: substratools (~=0.13.0)
Requires-Dist: pydantic (>=1.9.0)
Requires-Dist: pip (>=21.2)
Requires-Dist: wheel
Requires-Dist: six
Requires-Dist: packaging
Provides-Extra: dev
Requires-Dist: pytest (>=6.2.4) ; extra == 'dev'
Requires-Dist: pytest-cov (>=2.12.0) ; extra == 'dev'
Requires-Dist: pre-commit (>=2.13.0) ; extra == 'dev'
Requires-Dist: types-PyYAML (>=6.0.0) ; extra == 'dev'
Requires-Dist: torch (>=1.9.1) ; extra == 'dev'
Requires-Dist: nbmake (>=1.1) ; extra == 'dev'
